{
  "name": "👅 Preliminaries",
  "variables": {
    "penis_saliva": {
      "hide": true,
      "tags": "{penis}, saliva on penis, {saliva}"
    }
  },
  "tags": {
    "action": {
      "group_labels": true,
      "tags": {
        "fingering": {
          "tags": {
            "fingering_action": {
              "number": [0, 3],
              "tags": ["fingering", "anal fingering", "fingering from behind"]
            },
            "fingering_extra": "{pussy}, {pussy_juice}"
          }
        },
        "fellatio": "fellatio, {penis_saliva}",
        "deepthroat": "deepthroat, {penis_saliva}",
        "licking penis": "licking penis, tongue out, {penis_saliva}",
        "handjob": "handjob, {penis}, {precum}",
        "paizuri": {
          "number": [1, 2],
          "tags": ["straddling ", "handsfree "],
          "suffix": "paizuri, {nipples}, {penis}, {precum}"
        }
      }
    }
  }
}
